kerasfactory/__init__.py
kerasfactory/layers/AdvancedGraphFeature.py
kerasfactory/layers/AdvancedNumericalEmbedding.py
kerasfactory/layers/BoostingBlock.py
kerasfactory/layers/BoostingEnsembleLayer.py
kerasfactory/layers/BusinessRulesLayer.py
kerasfactory/layers/CastToFloat32Layer.py
kerasfactory/layers/CategoricalAnomalyDetectionLayer.py
kerasfactory/layers/ColumnAttention.py
kerasfactory/layers/DFTSeriesDecomposition.py
kerasfactory/layers/DataEmbeddingWithoutPosition.py
kerasfactory/layers/DateEncodingLayer.py
kerasfactory/layers/DateParsingLayer.py
kerasfactory/layers/DifferentiableTabularPreprocessor.py
kerasfactory/layers/DifferentialPreprocessingLayer.py
kerasfactory/layers/DistributionAwareEncoder.py
kerasfactory/layers/DistributionTransformLayer.py
kerasfactory/layers/FeatureCutout.py
kerasfactory/layers/FeatureMixing.py
kerasfactory/layers/FixedEmbedding.py
kerasfactory/layers/GatedFeatureFusion.py
kerasfactory/layers/GatedFeaturesSelection.py
kerasfactory/layers/GatedLinearUnit.py
kerasfactory/layers/GatedResidualNetwork.py
kerasfactory/layers/GraphFeatureAggregation.py
kerasfactory/layers/HyperZZWOperator.py
kerasfactory/layers/InterpretableMultiHeadAttention.py
kerasfactory/layers/MixingLayer.py
kerasfactory/layers/MovingAverage.py
kerasfactory/layers/MultiHeadGraphFeaturePreprocessor.py
kerasfactory/layers/MultiResolutionTabularAttention.py
kerasfactory/layers/MultiScaleSeasonMixing.py
kerasfactory/layers/MultiScaleTrendMixing.py
kerasfactory/layers/NumericalAnomalyDetection.py
kerasfactory/layers/PastDecomposableMixing.py
kerasfactory/layers/PositionalEmbedding.py
kerasfactory/layers/ReversibleInstanceNorm.py
kerasfactory/layers/ReversibleInstanceNormMultivariate.py
kerasfactory/layers/RowAttention.py
kerasfactory/layers/SeasonLayer.py
kerasfactory/layers/SeriesDecomposition.py
kerasfactory/layers/SlowNetwork.py
kerasfactory/layers/SparseAttentionWeighting.py
kerasfactory/layers/StochasticDepth.py
kerasfactory/layers/TabularAttention.py
kerasfactory-0.1.0.dist-info/METADATA
kerasfactory-0.1.0.dist-info/WHEEL
kerasfactory-0.1.0.dist-info/licenses/LICENSE
kerasfactory-0.1.0.dist-info/RECORD
