Metadata-Version: 2.4
Name: kerasfactory
Version: 0.1.0
Summary: Reusable Model Architecture Bricks in Keras - Enterprise AI by UnicoLab
License: MIT
License-File: LICENSE
Keywords: keras,tensorflow,machine-learning,deep-learning,tabular-data,attention,neural-networks,unicolab,enterprise-ai
Author: UnicoLab
Author-email: contact@unicolab.ai
Requires-Python: >=3.10,<3.13
Classifier: Development Status :: 4 - Beta
Classifier: Intended Audience :: Developers
Classifier: Intended Audience :: Science/Research
Classifier: License :: OSI Approved :: MIT License
Classifier: Operating System :: OS Independent
Classifier: Programming Language :: Python :: 3
Classifier: Programming Language :: Python :: 3.10
Classifier: Programming Language :: Python :: 3.11
Classifier: Programming Language :: Python :: 3.12
Classifier: Topic :: Office/Business
Classifier: Topic :: Scientific/Engineering :: Artificial Intelligence
Classifier: Topic :: Software Development :: Libraries :: Python Modules
Requires-Dist: keras (>=3.8.0,<4.0.0)
Requires-Dist: loguru (>=0.7.2,<0.8.0)
Requires-Dist: pandas (>=2.2.3,<3.0.0)
Requires-Dist: pytest (>=8.3.4,<9.0.0)
Project-URL: Documentation, https://unicolab.github.io/KerasFactory/
Project-URL: Homepage, https://unicolab.ai
Project-URL: Repository, https://github.com/UnicoLab/KerasFactory
